Metadata-Version: 2.1
Name: prometheus_logging
Version: 0.1.0
Summary: A simple logging library for ML projects using Prometheus
Home-page: https://github.com/yourusername/prometheus_logging
Author: Your Name
Author-email: your.email@example.com
Classifier: Programming Language :: Python :: 3
Classifier: License :: OSI Approved :: MIT License
Classifier: Operating System :: OS Independent
Requires-Python: >=3.6
License-File: LICENSE
Requires-Dist: prometheus_client
Requires-Dist: psutil
